{
"type": "FeatureCollection",
"name": "point4326_NY_json",
"crs": { "type": "name", "properties": { "name": "urn:ogc:def:crs:OGC:1.3:CRS84" } },
"features": [
{ "type": "Feature", "properties": { "id": 1 }, "geometry": { "type": "Point", "coordinates": [ -73.928159650885192, 40.755800000932474 ] } }
]
}
